{
  "date": "2026-07-06",
  "generated_at": "2026-07-06T15:11:14.947309+08:00",
  "key_themes": [
    {
      "title": "中東戰爭對全球經濟的影響",
      "background": "中東戰爭持續對全球經濟產生重大影響，能源價格上升對全球經濟造成雙重挑戰",
      "development": "俄羅斯近期再度轟炸烏克蘭首都基輔，造成至少10人死亡，46人受傷，包括5名兒童。這是基輔在一周內遭受俄羅斯轟炸的第二次。事件背景是俄羅斯近期對烏克蘭的軍事行動加劇",
      "impact": "這次轟炸對烏克蘭人民的影響，包括心理和物質上的傷害。預計這次轟炸將會對全球能源市場產生重大影響，導致能源價格上升",
      "conclusion": "短線避險情緒將持續壓低美股，但若週末停火談判有進展，週一可能出現技術反彈",
      "region": "global"
    },
    {
      "title": "人工智慧產業的快速發展",
      "background": "人工智慧產業的快速發展推動各個行業的變革",
      "development": "美國富人中，有一部分人選擇讓AI取代傳統學校教育來教導孩子。這種選擇可能是由於富人對AI的信任程度較高，或者是希望為孩子提供更個人化的教育體驗",
      "impact": "這種選擇可能會對傳統教育產業產生重大影響，同時也引發了對AI教育的關注，是否能夠取代傳統學校教育的問題仍存疑",
      "conclusion": "人工智慧產業的快速發展將會對各個行業產生重大影響，包括教育產業",
      "region": "americas"
    },
    {
      "title": "全球能源市場的變化",
      "background": "全球能源市場的變化影響投資者",
      "development": "關島因為超級颱風巴威的接近，政府已經下令疏散居民。預測颱風將於星期一登陸，風速可達每小時 160 公里，海浪高達 11 米",
      "impact": "超級颱風巴威的來臨將會對關島造成嚴重的破壞，政府正在做好應對措施。這次事件可能會對全球能源市場產生重大影響，導致能源價格上升",
      "conclusion": "全球能源市場的變化將會對投資者產生重大影響，投資者需要密切關注市場的變化",
      "region": "asia"
    }
  ],
  "sector_analysis": [
    {
      "sector": "能源",
      "direction": "看空",
      "reasoning": "全球能源市場的變化和超級颱風巴威的來臨將會對能源價格產生重大影響",
      "key_ticker": "原油"
    },
    {
      "sector": "科技",
      "direction": "看多",
      "reasoning": "人工智慧產業的快速發展將會對各個行業產生重大影響",
      "key_ticker": "AI"
    },
    {
      "sector": "金融",
      "direction": "中性",
      "reasoning": "全球經濟的不確定性和挑戰將會對金融市場產生重大影響",
      "key_ticker": "S&P500"
    }
  ],
  "action_signals": [
    {
      "asset": "原油",
      "signal": "短空",
      "reasoning": "全球能源市場的變化和超級颱風巴威的來臨將會對能源價格產生重大影響",
      "confidence": "高"
    },
    {
      "asset": "AI",
      "signal": "短多",
      "reasoning": "人工智慧產業的快速發展將會對各個行業產生重大影響",
      "confidence": "中高"
    },
    {
      "asset": "S&P500",
      "signal": "觀望",
      "reasoning": "全球經濟的不確定性和挑戰將會對金融市場產生重大影響",
      "confidence": "中"
    }
  ],
  "risk_radar": [
    {
      "event": "中東戰爭升級",
      "probability": "高",
      "impact": "高",
      "timeframe": "本週",
      "description": "中東戰爭升級將會對全球能源市場產生重大影響，導致能源價格上升"
    },
    {
      "event": "超級颱風巴威登陸",
      "probability": "中",
      "impact": "中",
      "timeframe": "下週",
      "description": "超級颱風巴威登陸將會對關島造成嚴重的破壞，政府正在做好應對措施"
    },
    {
      "event": "人工智慧產業的快速發展",
      "probability": "高",
      "impact": "高",
      "timeframe": "本月",
      "description": "人工智慧產業的快速發展將會對各個行業產生重大影響，包括教育產業"
    }
  ],
  "narrative_shift": {
    "new_themes": [
      "中東戰爭升級"
    ],
    "escalated": [
      "全球能源市場的變化"
    ],
    "cooled": [
      "人工智慧產業的快速發展"
    ],
    "disappeared": [
      "金融市場的波動"
    ]
  },
  "watch_next": [
    {
      "topic": "中東戰爭升級",
      "reason": "中東戰爭升級將會對全球能源市場產生重大影響",
      "timeframe": "本週"
    },
    {
      "topic": "超級颱風巴威登陸",
      "reason": "超級颱風巴威登陸將會對關島造成嚴重的破壞",
      "timeframe": "下週"
    },
    {
      "topic": "人工智慧產業的快速發展",
      "reason": "人工智慧產業的快速發展將會對各個行業產生重大影響",
      "timeframe": "本月"
    }
  ],
  "cross_links": [
    {
      "themes": [
        "中東戰爭升級",
        "全球能源市場的變化"
      ],
      "chain": "中東戰爭升級 → 全球能源市場的變化 → 能源價格上升"
    },
    {
      "themes": [
        "人工智慧產業的快速發展",
        "教育產業"
      ],
      "chain": "人工智慧產業的快速發展 → 教育產業 → AI教育"
    },
    {
      "themes": [
        "超級颱風巴威登陸",
        "關島"
      ],
      "chain": "超級颱風巴威登陸 → 關島 → 破壞"
    }
  ],
  "market_snapshot": {
    "mood": "避險",
    "key_moves": "VIX 恐慌指數下跌 2.65%、原油 WTI 下跌 0.01%、黃金上漲 1.15%、S&P500 漲 0.00%、那斯達克 跌 0.80%、台股 跌 0.48%、美元指數上漲 0.23%、美債10Y殖利率上漲 0.22%、美元/台幣上漲 0.48%"
  },
  "data_table": {
    "indices": [
      {
        "key": "SP500",
        "name": "S&P 500",
        "price": 7483.24,
        "change_pct": 0.0,
        "status": "danger"
      },
      {
        "key": "NASDAQ",
        "name": "那斯達克",
        "price": 25832.67,
        "change_pct": -0.8,
        "status": "normal"
      },
      {
        "key": "TWII",
        "name": "台股加權",
        "price": 46556.39,
        "change_pct": -0.48,
        "status": "danger"
      }
    ],
    "commodities": [
      {
        "key": "GOLD",
        "name": "黃金",
        "price": 4160.2,
        "change_pct": 1.15,
        "status": "normal"
      },
      {
        "key": "OIL",
        "name": "原油 WTI",
        "price": 68.68,
        "change_pct": -0.01,
        "status": "normal"
      }
    ],
    "forex": [
      {
        "key": "DXY",
        "name": "美元指數",
        "price": 101.09,
        "change_pct": 0.23,
        "status": "normal"
      },
      {
        "key": "USDTWD",
        "name": "美元/台幣",
        "price": 32.08,
        "change_pct": 0.48,
        "status": "normal"
      }
    ],
    "bonds_volatility": [
      {
        "key": "TNX",
        "name": "美債10Y殖利率",
        "price": 4.49,
        "change_pct": 0.22,
        "status": "normal"
      },
      {
        "key": "VIX",
        "name": "VIX 恐慌指數",
        "price": 16.15,
        "change_pct": -2.65,
        "status": "normal"
      }
    ]
  }
}