{
  "date": "2026-06-30",
  "generated_at": "2026-06-30T17:06:38.318159+08:00",
  "key_themes": [
    {
      "title": "全球經濟面臨挑戰",
      "background": "近期全球經濟面臨多重挑戰，包括中東戰爭、能源價格上升等",
      "development": "根據最新數據，VIX 恐慌指數上升，原油價格下跌，黃金價格上升，S&P500 指數上漲",
      "impact": "這些數據表明全球經濟仍然面臨不確定性和挑戰，投資者仍然謹慎",
      "conclusion": "短期內，全球經濟可能會繼續面臨挑戰，但長期來看，經濟仍然有望恢復",
      "region": "global"
    },
    {
      "title": "人工智慧產業發展",
      "background": "人工智慧產業近期發展迅速，各個公司都在投資人工智慧技術",
      "development": "根據最新消息，Salesforce 近日宣布三宗購併案，展現出對人工智慧領域的投資熱情",
      "impact": "這些購併案對 Salesforce 的未來發展將會產生重大影響，市場將會如何反應仍需觀察",
      "conclusion": "人工智慧產業仍然具有巨大的發展潛力，各個公司都在努力佈局",
      "region": "americas"
    },
    {
      "title": "亞洲經濟發展",
      "background": "亞洲經濟近期面臨多重挑戰，包括日本改革倒退等",
      "development": "根據最新消息，日本的經濟改革步伐似乎出現了倒退的跡象，外資投資者擔憂日本正在往經濟民族主義的方向倒退",
      "impact": "這一轉變可能會對日本的經濟發展產生重大影響，外資投資者擔憂這一轉變可能會導致日本的經濟發展遲緩",
      "conclusion": "亞洲經濟仍然面臨多重挑戰，各個國家都需要努力推動經濟發展",
      "region": "asia"
    }
  ],
  "sector_analysis": [
    {
      "sector": "科技",
      "direction": "看多",
      "reasoning": "人工智慧產業仍然具有巨大的發展潛力，各個公司都在努力佈局",
      "key_ticker": "Salesforce"
    },
    {
      "sector": "能源",
      "direction": "看空",
      "reasoning": "原油價格下跌，能源市場仍然面臨不確定性",
      "key_ticker": "原油"
    },
    {
      "sector": "金融",
      "direction": "中性",
      "reasoning": "全球經濟仍然面臨挑戰，金融市場仍然謹慎",
      "key_ticker": "S&P500"
    }
  ],
  "action_signals": [
    {
      "asset": "Salesforce",
      "signal": "短多",
      "reasoning": "Salesforce 近日宣布三宗購併案，展現出對人工智慧領域的投資熱情",
      "confidence": "高"
    },
    {
      "asset": "原油",
      "signal": "短空",
      "reasoning": "原油價格下跌，能源市場仍然面臨不確定性",
      "confidence": "中高"
    }
  ],
  "risk_radar": [
    {
      "event": "全球經濟面臨挑戰",
      "probability": "高",
      "impact": "高",
      "timeframe": "本週",
      "description": "全球經濟仍然面臨多重挑戰，包括中東戰爭、能源價格上升等"
    },
    {
      "event": "人工智慧產業發展",
      "probability": "中",
      "impact": "中",
      "timeframe": "下週",
      "description": "人工智慧產業仍然具有巨大的發展潛力，各個公司都在努力佈局"
    }
  ],
  "narrative_shift": {
    "new_themes": [
      "亞洲經濟發展"
    ],
    "escalated": [
      "全球經濟面臨挑戰"
    ],
    "cooled": [
      "人工智慧產業發展"
    ],
    "disappeared": []
  },
  "watch_next": [
    {
      "topic": "全球經濟發展",
      "reason": "全球經濟仍然面臨多重挑戰",
      "timeframe": "本週"
    },
    {
      "topic": "人工智慧產業發展",
      "reason": "人工智慧產業仍然具有巨大的發展潛力",
      "timeframe": "下週"
    }
  ],
  "cross_links": [
    {
      "themes": [
        "全球經濟面臨挑戰",
        "人工智慧產業發展"
      ],
      "chain": "全球經濟面臨挑戰→人工智慧產業發展→亞洲經濟發展"
    }
  ],
  "market_snapshot": {
    "mood": "觀望",
    "key_moves": "VIX 恐慌指數上升，原油價格下跌，黃金價格上升，S&P500 指數上漲"
  },
  "data_table": {
    "indices": [
      {
        "key": "SP500",
        "name": "S&P 500",
        "price": 7440.43,
        "change_pct": 1.18,
        "status": "danger"
      },
      {
        "key": "NASDAQ",
        "name": "那斯達克",
        "price": 25820.14,
        "change_pct": 2.07,
        "status": "normal"
      },
      {
        "key": "TWII",
        "name": "台股加權",
        "price": 46125.91,
        "change_pct": 2.5,
        "status": "danger"
      }
    ],
    "commodities": [
      {
        "key": "GOLD",
        "name": "黃金",
        "price": 4030.0,
        "change_pct": 0.19,
        "status": "normal"
      },
      {
        "key": "OIL",
        "name": "原油 WTI",
        "price": 70.49,
        "change_pct": -0.37,
        "status": "normal"
      }
    ],
    "forex": [
      {
        "key": "DXY",
        "name": "美元指數",
        "price": 101.37,
        "change_pct": 0.26,
        "status": "normal"
      },
      {
        "key": "USDTWD",
        "name": "美元/台幣",
        "price": 31.85,
        "change_pct": 0.01,
        "status": "normal"
      }
    ],
    "bonds_volatility": [
      {
        "key": "TNX",
        "name": "美債10Y殖利率",
        "price": 4.37,
        "change_pct": -0.46,
        "status": "normal"
      },
      {
        "key": "VIX",
        "name": "VIX 恐慌指數",
        "price": 17.75,
        "change_pct": 0.57,
        "status": "normal"
      }
    ]
  }
}